{
  "ad1": [
    {
      "des": "",
      "banner": "https://play-lh.googleusercontent.com/exrunBueUBmCoUpKhOm4AiLGH-bBvfjIkw5lIrTmYXHXK0dMViKMsuLwD0pllmGWl74",
      "image_path": "https://play-lh.googleusercontent.com/RF89VuSVruXFVfA7gdYyjpRHMu0wnXz43p8Tw4AGEVJ0WtWFraPtx8s-w5A_m-EdjQ=s180-rw",
      "ads_name": "Quotes And Ads Mania",
      "ads_Link": "https://play.google.com/store/apps/details?id=com.app.quotes_share_mania"
    },
    {
      "des": "",
      "banner": "",
      "image_path": "https://play-lh.googleusercontent.com/rqFTxBAoIdVb8pj2RUn7AvBZVgTYPXNvm-B6s_iJaltoZ9Xa-DqB3XgNxMrW1jKKVw=s180-rw",
      "ads_name": "HappyMod Free Mods",
      "ads_Link": ""
    },
    {
      "des": "",
      "banner": "",
      "image_path": "https://play-lh.googleusercontent.com/GJhQKAAXhYp2KrlY5FuZMnoPqn1wSxtoEYQGPabSS4hReXYven_DLw1vHYLoCAfdsXg=s180-rw",
      "ads_name": "Star Sports Live T20 WorldCup",
      "ads_Link": "https://play.google.com/store/apps/details?id=com.starsportssylvie.livecricketnineone.starsports"
    },
    {
      "des": "",
      "banner": "",
      "image_path": "https://play-lh.googleusercontent.com/dH8SLOXDZ8RkQPxqpfS69J0IuZGNgQznxRiSZd-sDKQfwdKEZW7FwNTZmlWZOfea3Jgq=s180-rw",
      "ads_name": "Picasso : Live Tv Show & Movies",
      "ads_Link": "https://play.google.com/store/apps/details?id=com.pikashowsylvie.pikashowmovieone.pikashow"
    },
    {
      "des": "",
      "banner": "",
      "image_path": "https://play-lh.googleusercontent.com/sKJ0uA73Hy7VlOUh6aVFNtlt2N3ELTyICfyghgJ-ZMyTJGay6tX9RLe_o9jceulegC7u=s180-rw",
      "ads_name": "Star Sports TV WorldCup 2021",
      "ads_Link": "https://play.google.com/store/apps/details?id=com.starsportssylvie.livecricketthreenine.starsports"
    },
    {
      "des": "",
      "banner": "",
      "image_path": "https://play-lh.googleusercontent.com/umbKL4DU6mXyHavJYIOCStxiE0IGYwcwSIR22tGReYsjMwCE3-27ScESl-qK4-HJo8M=s180-rw",
      "ads_name": "Tap Tap App Games",
      "ads_Link": "https://play.google.com/store/apps/details?id=com.tapttapsylvie.tapguidedtwo.taptapguide"
    },
    {
      "des": "",
      "banner": "",
      "image_path": "https://play-lh.googleusercontent.com/DI065sJ6o1ajrQxdRsr_8YQ5o4Y5DhV3YECwecm-wWmP6Kl0SBknLO1ez6B6WMpNww=s180-rw",
      "ads_name": "Picasso Live Cricket",
      "ads_Link": "https://play.google.com/store/apps/details?id=com.pikashowsylvie.pikashowmovietwo.pikashow"
    },
    {
      "des": "Zee Tv serial content includes Zee TV live,movies,series,TV shows ",
      "banner": "https://play-lh.googleusercontent.com/uDacobW0a9-4SRZs5hEGfX2bFm4nOWD8gCvBQEC40pkoa3VWIJ9bbGg2KGy_gfRMA10",
      "image_path": "https://play-lh.googleusercontent.com/wc3u6Z5L0xwg0kAklZH3s6887ZQTSC0z_bwN3uXq_Qa4iKXN0bOp6gM9sj0roQi4Hw=s180-rw",
      "ads_name": "Zee TV Serials - Guide On Zee TV Shows",
      "ads_Link": ""
    }
  ]
}
